ornament/__init__.py
ornament/__pkginfo__.py
ornament/patterns.py
tests/__init__.py
ornament-0.1.0.dist-info/METADATA
ornament-0.1.0.dist-info/WHEEL
ornament-0.1.0.dist-info/top_level.txt
ornament-0.1.0.dist-info/RECORD
