Metadata-Version: 2.1
Name: ornament
Version: 0.1.0
Summary: JSON/YAML homoiconic templating language
Home-page: https://github.com/scravy/ornament
Author: Julian Fleischer
Author-email: tirednesscankill@warhog.net
License: UNKNOWN
Platform: UNKNOWN
Classifier: Programming Language :: Python :: 3
Classifier: License :: OSI Approved :: MIT License
Classifier: Operating System :: OS Independent
Requires-Python: >=3.8
